atrader/__init__.py
atrader/enums.py
atrader/gencode.py
atrader/setting.py
atrader/api/__init__.py
atrader/api/bpfactor/__init__.py
atrader/api/bpfactor/_factors.cp311-win_amd64.pyd
atrader/api/bpfactor/convertor.cp311-win_amd64.pyd
atrader/api/fundamental/__init__.py
atrader/api/fundamental/convertor.cp311-win_amd64.pyd
atrader/api/fundamental/company/__init__.py
atrader/api/fundamental/company/equity.cp311-win_amd64.pyd
atrader/api/fundamental/company/fid.cp311-win_amd64.pyd
atrader/api/fundamental/company/info.cp311-win_amd64.pyd
atrader/api/fundamental/company/ipo.cp311-win_amd64.pyd
atrader/api/fundamental/company/matters.cp311-win_amd64.pyd
atrader/api/fundamental/company/personnel.cp311-win_amd64.pyd
atrader/api/fundamental/company/restricted.cp311-win_amd64.pyd
atrader/api/fundamental/fdmt/__init__.py
atrader/api/fundamental/fdmt/bs.cp311-win_amd64.pyd
atrader/api/fundamental/fdmt/cf.cp311-win_amd64.pyd
atrader/api/fundamental/fdmt/expectation.cp311-win_amd64.pyd
atrader/api/fundamental/fdmt/indicator.cp311-win_amd64.pyd
atrader/api/fundamental/fdmt/ins.cp311-win_amd64.pyd
atrader/api/fundamental/fdmt/note.cp311-win_amd64.pyd
atrader/api/fundamental/mkt/__init__.py
atrader/api/fundamental/mkt/mkt.cp311-win_amd64.pyd
atrader/api/history/__init__.py
atrader/api/history/_history.cp311-win_amd64.pyd
atrader/api/history/convertor.cp311-win_amd64.pyd
atrader/api/orders/__init__.py
atrader/api/regfuncs/__init__.py
atrader/api/regfuncs/_regfuncs.cp311-win_amd64.pyd
atrader/api/regfuncs/convertor.cp311-win_amd64.pyd
atrader/api/riskmodel/__init__.py
atrader/api/riskmodel/convertor.cp311-win_amd64.pyd
atrader/api/riskmodel/rm.cp311-win_amd64.pyd
atrader/backtest/__init__.py
atrader/backtest/apiimpl.cp311-win_amd64.pyd
atrader/backtest/convertor.cp311-win_amd64.pyd
atrader/backtest/domain.cp311-win_amd64.pyd
atrader/backtest/main.cp311-win_amd64.pyd
atrader/backtest/syscls.cp311-win_amd64.pyd
atrader/backtest/model/__init__.py
atrader-4.2.0.0.dist-info/LICENSE
atrader-4.2.0.0.dist-info/METADATA
atrader-4.2.0.0.dist-info/WHEEL
atrader-4.2.0.0.dist-info/top_level.txt
atrader-4.2.0.0.dist-info/RECORD
