Metadata-Version: 2.1
Name: atrader
Version: 4.2.0.0
Summary: AT-edu，量化研究交易教学实践平台，简称：AT-edu 教学平台
Home-page: 
Author: Digquant Technoloy
Author-email: Contact@digquant.com
License: LICENSE
Keywords: quantitative,trading
Classifier: Development Status :: 3 - Alpha
Classifier: Intended Audience :: Developers
Classifier: Programming Language :: Python
Classifier: Operating System :: Microsoft :: Windows
Classifier: Programming Language :: Cython
Classifier: Programming Language :: Python :: 3.5
License-File: LICENSE
Requires-Dist: enum34 (>=1.1.6)
Requires-Dist: six (>=1.11.0)
Requires-Dist: pytz (>=2017.3.0)
Requires-Dist: python-dateutil (>=2.6.1)
Requires-Dist: numpy (<=1.26.0,>=1.22.0)
Requires-Dist: scipy (>=1.0.0)
Requires-Dist: pandas (<=2.1.1,>=1.5.0)
